{
  "generated_ts": 1750000000.0,
  "n_resolved": 120,
  "by_lead": [
    {"lead_hours": 72, "model_brier": 0.183, "market_brier": 0.211, "model_logloss": 0.524, "market_logloss": 0.601, "n": 30},
    {"lead_hours": 48, "model_brier": 0.191, "market_brier": 0.203, "model_logloss": 0.548, "market_logloss": 0.579, "n": 30},
    {"lead_hours": 24, "model_brier": 0.198, "market_brier": 0.199, "model_logloss": 0.567, "market_logloss": 0.568, "n": 30},
    {"lead_hours": 6, "model_brier": 0.212, "market_brier": 0.188, "model_logloss": 0.601, "market_logloss": 0.537, "n": 30}
  ],
  "rows": [
    {"city": "New York", "lead_hours": 72, "outcome": 1, "model_prob": 0.75, "market_prob": 0.65},
    {"city": "New York", "lead_hours": 72, "outcome": 0, "model_prob": 0.28, "market_prob": 0.38},
    {"city": "New York", "lead_hours": 72, "outcome": 1, "model_prob": 0.82, "market_prob": 0.70},
    {"city": "New York", "lead_hours": 72, "outcome": 0, "model_prob": 0.15, "market_prob": 0.25},
    {"city": "New York", "lead_hours": 72, "outcome": 1, "model_prob": 0.68, "market_prob": 0.55},
    {"city": "New York", "lead_hours": 72, "outcome": 1, "model_prob": 0.91, "market_prob": 0.80},
    {"city": "New York", "lead_hours": 48, "outcome": 0, "model_prob": 0.22, "market_prob": 0.30},
    {"city": "New York", "lead_hours": 48, "outcome": 1, "model_prob": 0.77, "market_prob": 0.72},
    {"city": "New York", "lead_hours": 48, "outcome": 0, "model_prob": 0.31, "market_prob": 0.28},
    {"city": "New York", "lead_hours": 48, "outcome": 1, "model_prob": 0.85, "market_prob": 0.82},
    {"city": "New York", "lead_hours": 48, "outcome": 0, "model_prob": 0.18, "market_prob": 0.20},
    {"city": "New York", "lead_hours": 48, "outcome": 1, "model_prob": 0.62, "market_prob": 0.68},
    {"city": "New York", "lead_hours": 24, "outcome": 1, "model_prob": 0.78, "market_prob": 0.80},
    {"city": "New York", "lead_hours": 24, "outcome": 0, "model_prob": 0.25, "market_prob": 0.22},
    {"city": "New York", "lead_hours": 24, "outcome": 1, "model_prob": 0.70, "market_prob": 0.74},
    {"city": "New York", "lead_hours": 24, "outcome": 0, "model_prob": 0.33, "market_prob": 0.30},
    {"city": "New York", "lead_hours": 24, "outcome": 1, "model_prob": 0.88, "market_prob": 0.91},
    {"city": "New York", "lead_hours": 24, "outcome": 0, "model_prob": 0.19, "market_prob": 0.15},
    {"city": "New York", "lead_hours": 6, "outcome": 1, "model_prob": 0.72, "market_prob": 0.85},
    {"city": "New York", "lead_hours": 6, "outcome": 0, "model_prob": 0.29, "market_prob": 0.12},
    {"city": "New York", "lead_hours": 6, "outcome": 1, "model_prob": 0.65, "market_prob": 0.89},
    {"city": "New York", "lead_hours": 6, "outcome": 0, "model_prob": 0.35, "market_prob": 0.08},
    {"city": "New York", "lead_hours": 6, "outcome": 1, "model_prob": 0.58, "market_prob": 0.92},
    {"city": "New York", "lead_hours": 6, "outcome": 0, "model_prob": 0.41, "market_prob": 0.05},
    {"city": "Los Angeles", "lead_hours": 72, "outcome": 0, "model_prob": 0.20, "market_prob": 0.30},
    {"city": "Los Angeles", "lead_hours": 72, "outcome": 1, "model_prob": 0.78, "market_prob": 0.65},
    {"city": "Los Angeles", "lead_hours": 72, "outcome": 0, "model_prob": 0.12, "market_prob": 0.22},
    {"city": "Los Angeles", "lead_hours": 72, "outcome": 1, "model_prob": 0.85, "market_prob": 0.71},
    {"city": "Los Angeles", "lead_hours": 72, "outcome": 0, "model_prob": 0.25, "market_prob": 0.40},
    {"city": "Los Angeles", "lead_hours": 72, "outcome": 1, "model_prob": 0.73, "market_prob": 0.58},
    {"city": "Los Angeles", "lead_hours": 48, "outcome": 0, "model_prob": 0.18, "market_prob": 0.25},
    {"city": "Los Angeles", "lead_hours": 48, "outcome": 1, "model_prob": 0.80, "market_prob": 0.75},
    {"city": "Los Angeles", "lead_hours": 48, "outcome": 0, "model_prob": 0.22, "market_prob": 0.28},
    {"city": "Los Angeles", "lead_hours": 48, "outcome": 1, "model_prob": 0.75, "market_prob": 0.70},
    {"city": "Los Angeles", "lead_hours": 48, "outcome": 0, "model_prob": 0.30, "market_prob": 0.35},
    {"city": "Los Angeles", "lead_hours": 48, "outcome": 1, "model_prob": 0.68, "market_prob": 0.65},
    {"city": "Los Angeles", "lead_hours": 24, "outcome": 1, "model_prob": 0.82, "market_prob": 0.84},
    {"city": "Los Angeles", "lead_hours": 24, "outcome": 0, "model_prob": 0.20, "market_prob": 0.18},
    {"city": "Los Angeles", "lead_hours": 24, "outcome": 1, "model_prob": 0.76, "market_prob": 0.79},
    {"city": "Los Angeles", "lead_hours": 24, "outcome": 0, "model_prob": 0.28, "market_prob": 0.24},
    {"city": "Los Angeles", "lead_hours": 24, "outcome": 1, "model_prob": 0.70, "market_prob": 0.75},
    {"city": "Los Angeles", "lead_hours": 24, "outcome": 0, "model_prob": 0.32, "market_prob": 0.29},
    {"city": "Los Angeles", "lead_hours": 6, "outcome": 1, "model_prob": 0.68, "market_prob": 0.88},
    {"city": "Los Angeles", "lead_hours": 6, "outcome": 0, "model_prob": 0.32, "market_prob": 0.10},
    {"city": "Los Angeles", "lead_hours": 6, "outcome": 1, "model_prob": 0.60, "market_prob": 0.91},
    {"city": "Los Angeles", "lead_hours": 6, "outcome": 0, "model_prob": 0.38, "market_prob": 0.07},
    {"city": "Los Angeles", "lead_hours": 6, "outcome": 1, "model_prob": 0.55, "market_prob": 0.93},
    {"city": "Los Angeles", "lead_hours": 6, "outcome": 0, "model_prob": 0.42, "market_prob": 0.06},
    {"city": "Chicago", "lead_hours": 72, "outcome": 1, "model_prob": 0.70, "market_prob": 0.58},
    {"city": "Chicago", "lead_hours": 72, "outcome": 0, "model_prob": 0.25, "market_prob": 0.38},
    {"city": "Chicago", "lead_hours": 72, "outcome": 1, "model_prob": 0.80, "market_prob": 0.65},
    {"city": "Chicago", "lead_hours": 72, "outcome": 0, "model_prob": 0.18, "market_prob": 0.32},
    {"city": "Chicago", "lead_hours": 72, "outcome": 1, "model_prob": 0.75, "market_prob": 0.60},
    {"city": "Chicago", "lead_hours": 72, "outcome": 0, "model_prob": 0.22, "market_prob": 0.35},
    {"city": "Chicago", "lead_hours": 48, "outcome": 0, "model_prob": 0.28, "market_prob": 0.33},
    {"city": "Chicago", "lead_hours": 48, "outcome": 1, "model_prob": 0.72, "market_prob": 0.68},
    {"city": "Chicago", "lead_hours": 48, "outcome": 0, "model_prob": 0.20, "market_prob": 0.25},
    {"city": "Chicago", "lead_hours": 48, "outcome": 1, "model_prob": 0.78, "market_prob": 0.74},
    {"city": "Chicago", "lead_hours": 48, "outcome": 0, "model_prob": 0.33, "market_prob": 0.30},
    {"city": "Chicago", "lead_hours": 48, "outcome": 1, "model_prob": 0.65, "market_prob": 0.62},
    {"city": "Chicago", "lead_hours": 24, "outcome": 1, "model_prob": 0.74, "market_prob": 0.77},
    {"city": "Chicago", "lead_hours": 24, "outcome": 0, "model_prob": 0.27, "market_prob": 0.24},
    {"city": "Chicago", "lead_hours": 24, "outcome": 1, "model_prob": 0.80, "market_prob": 0.82},
    {"city": "Chicago", "lead_hours": 24, "outcome": 0, "model_prob": 0.22, "market_prob": 0.20},
    {"city": "Chicago", "lead_hours": 24, "outcome": 1, "model_prob": 0.68, "market_prob": 0.72},
    {"city": "Chicago", "lead_hours": 24, "outcome": 0, "model_prob": 0.35, "market_prob": 0.31},
    {"city": "Chicago", "lead_hours": 6, "outcome": 1, "model_prob": 0.70, "market_prob": 0.87},
    {"city": "Chicago", "lead_hours": 6, "outcome": 0, "model_prob": 0.30, "market_prob": 0.11},
    {"city": "Chicago", "lead_hours": 6, "outcome": 1, "model_prob": 0.62, "market_prob": 0.90},
    {"city": "Chicago", "lead_hours": 6, "outcome": 0, "model_prob": 0.38, "market_prob": 0.09},
    {"city": "Chicago", "lead_hours": 6, "outcome": 1, "model_prob": 0.55, "market_prob": 0.94},
    {"city": "Chicago", "lead_hours": 6, "outcome": 0, "model_prob": 0.44, "market_prob": 0.04},
    {"city": "Miami", "lead_hours": 72, "outcome": 1, "model_prob": 0.72, "market_prob": 0.60},
    {"city": "Miami", "lead_hours": 72, "outcome": 0, "model_prob": 0.23, "market_prob": 0.36},
    {"city": "Miami", "lead_hours": 72, "outcome": 1, "model_prob": 0.83, "market_prob": 0.68},
    {"city": "Miami", "lead_hours": 72, "outcome": 0, "model_prob": 0.17, "market_prob": 0.30},
    {"city": "Miami", "lead_hours": 72, "outcome": 1, "model_prob": 0.76, "market_prob": 0.62},
    {"city": "Miami", "lead_hours": 72, "outcome": 0, "model_prob": 0.20, "market_prob": 0.33},
    {"city": "Miami", "lead_hours": 48, "outcome": 0, "model_prob": 0.24, "market_prob": 0.29},
    {"city": "Miami", "lead_hours": 48, "outcome": 1, "model_prob": 0.76, "market_prob": 0.71},
    {"city": "Miami", "lead_hours": 48, "outcome": 0, "model_prob": 0.28, "market_prob": 0.32},
    {"city": "Miami", "lead_hours": 48, "outcome": 1, "model_prob": 0.72, "market_prob": 0.68},
    {"city": "Miami", "lead_hours": 48, "outcome": 0, "model_prob": 0.32, "market_prob": 0.36},
    {"city": "Miami", "lead_hours": 48, "outcome": 1, "model_prob": 0.68, "market_prob": 0.65},
    {"city": "Miami", "lead_hours": 24, "outcome": 1, "model_prob": 0.80, "market_prob": 0.82},
    {"city": "Miami", "lead_hours": 24, "outcome": 0, "model_prob": 0.22, "market_prob": 0.19},
    {"city": "Miami", "lead_hours": 24, "outcome": 1, "model_prob": 0.74, "market_prob": 0.77},
    {"city": "Miami", "lead_hours": 24, "outcome": 0, "model_prob": 0.28, "market_prob": 0.25},
    {"city": "Miami", "lead_hours": 24, "outcome": 1, "model_prob": 0.70, "market_prob": 0.73},
    {"city": "Miami", "lead_hours": 24, "outcome": 0, "model_prob": 0.30, "market_prob": 0.27},
    {"city": "Miami", "lead_hours": 6, "outcome": 1, "model_prob": 0.66, "market_prob": 0.86},
    {"city": "Miami", "lead_hours": 6, "outcome": 0, "model_prob": 0.34, "market_prob": 0.12},
    {"city": "Miami", "lead_hours": 6, "outcome": 1, "model_prob": 0.58, "market_prob": 0.90},
    {"city": "Miami", "lead_hours": 6, "outcome": 0, "model_prob": 0.40, "market_prob": 0.08},
    {"city": "Miami", "lead_hours": 6, "outcome": 1, "model_prob": 0.52, "market_prob": 0.92},
    {"city": "Miami", "lead_hours": 6, "outcome": 0, "model_prob": 0.46, "market_prob": 0.06},
    {"city": "Austin", "lead_hours": 72, "outcome": 1, "model_prob": 0.74, "market_prob": 0.62},
    {"city": "Austin", "lead_hours": 72, "outcome": 0, "model_prob": 0.21, "market_prob": 0.34},
    {"city": "Austin", "lead_hours": 72, "outcome": 1, "model_prob": 0.84, "market_prob": 0.70},
    {"city": "Austin", "lead_hours": 72, "outcome": 0, "model_prob": 0.16, "market_prob": 0.28},
    {"city": "Austin", "lead_hours": 72, "outcome": 1, "model_prob": 0.77, "market_prob": 0.63},
    {"city": "Austin", "lead_hours": 72, "outcome": 0, "model_prob": 0.19, "market_prob": 0.31},
    {"city": "Austin", "lead_hours": 48, "outcome": 0, "model_prob": 0.26, "market_prob": 0.31},
    {"city": "Austin", "lead_hours": 48, "outcome": 1, "model_prob": 0.74, "market_prob": 0.69},
    {"city": "Austin", "lead_hours": 48, "outcome": 0, "model_prob": 0.29, "market_prob": 0.34},
    {"city": "Austin", "lead_hours": 48, "outcome": 1, "model_prob": 0.71, "market_prob": 0.67},
    {"city": "Austin", "lead_hours": 48, "outcome": 0, "model_prob": 0.34, "market_prob": 0.38},
    {"city": "Austin", "lead_hours": 48, "outcome": 1, "model_prob": 0.66, "market_prob": 0.63},
    {"city": "Austin", "lead_hours": 24, "outcome": 1, "model_prob": 0.78, "market_prob": 0.80},
    {"city": "Austin", "lead_hours": 24, "outcome": 0, "model_prob": 0.24, "market_prob": 0.21},
    {"city": "Austin", "lead_hours": 24, "outcome": 1, "model_prob": 0.72, "market_prob": 0.75},
    {"city": "Austin", "lead_hours": 24, "outcome": 0, "model_prob": 0.29, "market_prob": 0.26},
    {"city": "Austin", "lead_hours": 24, "outcome": 1, "model_prob": 0.68, "market_prob": 0.71},
    {"city": "Austin", "lead_hours": 24, "outcome": 0, "model_prob": 0.33, "market_prob": 0.29},
    {"city": "Austin", "lead_hours": 6, "outcome": 1, "model_prob": 0.64, "market_prob": 0.87},
    {"city": "Austin", "lead_hours": 6, "outcome": 0, "model_prob": 0.36, "market_prob": 0.11},
    {"city": "Austin", "lead_hours": 6, "outcome": 1, "model_prob": 0.56, "market_prob": 0.91},
    {"city": "Austin", "lead_hours": 6, "outcome": 0, "model_prob": 0.42, "market_prob": 0.07},
    {"city": "Austin", "lead_hours": 6, "outcome": 1, "model_prob": 0.50, "market_prob": 0.93},
    {"city": "Austin", "lead_hours": 6, "outcome": 0, "model_prob": 0.47, "market_prob": 0.05}
  ]
}
